hydra_filter_sweeper/__init__.py
hydra_filter_sweeper/filters.py
hydra_plugins/filter.py
hydra_filter_sweeper-2.1.0.dist-info/METADATA
hydra_filter_sweeper-2.1.0.dist-info/WHEEL
hydra_filter_sweeper-2.1.0.dist-info/licenses/LICENSE
hydra_filter_sweeper-2.1.0.dist-info/RECORD
