Metadata-Version: 2.4
Name: hydra-filter-sweeper
Version: 2.1.0
Summary: A Hydra plugin to extend the basic sweeper with customizable filters.
Project-URL: Repository, https://github.com/autrainer/hydra-filter-sweeper
Author-email: Simon Rampp <simon.rampp@tum.de>
License-Expression: MIT
License-File: LICENSE
Keywords: filter,hydra,plugin,sweeper
Classifier: Operating System :: OS Independent
Classifier: Programming Language :: Python :: 3
Classifier: Programming Language :: Python :: 3.9
Classifier: Programming Language :: Python :: 3.10
Classifier: Programming Language :: Python :: 3.11
Classifier: Programming Language :: Python :: 3.12
Requires-Python: ~=3.9
Requires-Dist: evalidate<3,>=2.0.3
Requires-Dist: hydra-core<2,>=1.3.2
